tprofiler/__init__.py
tprofiler/core.py
tprofiler-2.0.0.dist-info/LICENSE
tprofiler-2.0.0.dist-info/METADATA
tprofiler-2.0.0.dist-info/WHEEL
tprofiler-2.0.0.dist-info/entry_points.txt
tprofiler-2.0.0.dist-info/top_level.txt
tprofiler-2.0.0.dist-info/RECORD
