Metadata-Version: 2.2
Name: tprofiler
Version: 2.0.0
Summary: A combined time and memory profiler using psutil
Home-page: https://github.com/1ssb/tprofile
Author: Subhransu S. Bhattacharjee
Author-email: Subhransu.Bhattacharjee@anu.edu.au
Classifier: Programming Language :: Python :: 3
Classifier: Operating System :: OS Independent
License-File: LICENSE
Requires-Dist: psutil
Requires-Dist: line_profiler
Dynamic: author
Dynamic: author-email
Dynamic: classifier
Dynamic: description
Dynamic: description-content-type
Dynamic: home-page
Dynamic: requires-dist
Dynamic: summary
